sample_oeg_pip_package/__init__.py
sample_oeg_pip_package-0.1.dist-info/DESCRIPTION.rst
sample_oeg_pip_package-0.1.dist-info/METADATA
sample_oeg_pip_package-0.1.dist-info/RECORD
sample_oeg_pip_package-0.1.dist-info/WHEEL
sample_oeg_pip_package-0.1.dist-info/metadata.json
sample_oeg_pip_package-0.1.dist-info/top_level.txt
