Metadata-Version: 2.0
Name: sample-oeg-pip-package
Version: 0.1
Summary: Sample OEG pip package
Home-page: http://github.com/oeg-upm/sample-oeg-pip-package
Author: Daniel Doña
Author-email: ddona@delicias.dia.fi.upm.es
License: MIT
Platform: UNKNOWN
